pore_mapper/__init__.py
pore_mapper/_version.py
pore_mapper/_internal/atom.py
pore_mapper/_internal/bead.py
pore_mapper/_internal/blob.py
pore_mapper/_internal/host.py
pore_mapper/_internal/inflater.py
pore_mapper/_internal/pore.py
pore_mapper/_internal/radii.py
pore_mapper/_internal/result.py
pore_mapper/_internal/utilities.py
PoreMapper-2023.11.9.0.dist-info/LICENSE
PoreMapper-2023.11.9.0.dist-info/METADATA
PoreMapper-2023.11.9.0.dist-info/WHEEL
PoreMapper-2023.11.9.0.dist-info/top_level.txt
PoreMapper-2023.11.9.0.dist-info/RECORD
